dasein/__init__.py
dasein/advice_format.py
dasein/api.py
dasein/capture.py
dasein/config.py
dasein/events.py
dasein/extractors.py
dasein/microturn.py
dasein/pipecleaner.py
dasein/trace_buffer.py
dasein/types.py
dasein/wrappers.py
dasein/models/en_core_web_sm/en_core_web_sm/__init__.py
dasein/models/en_core_web_sm/en_core_web_sm/meta.json
dasein/models/en_core_web_sm/en_core_web_sm/en_core_web_sm-3.7.1/LICENSE
dasein/models/en_core_web_sm/en_core_web_sm/en_core_web_sm-3.7.1/LICENSES_SOURCES
dasein/models/en_core_web_sm/en_core_web_sm/en_core_web_sm-3.7.1/README.md
dasein/models/en_core_web_sm/en_core_web_sm/en_core_web_sm-3.7.1/accuracy.json
dasein/models/en_core_web_sm/en_core_web_sm/en_core_web_sm-3.7.1/config.cfg
dasein/models/en_core_web_sm/en_core_web_sm/en_core_web_sm-3.7.1/meta.json
dasein/models/en_core_web_sm/en_core_web_sm/en_core_web_sm-3.7.1/tokenizer
dasein/models/en_core_web_sm/en_core_web_sm/en_core_web_sm-3.7.1/attribute_ruler/patterns
dasein/models/en_core_web_sm/en_core_web_sm/en_core_web_sm-3.7.1/lemmatizer/lookups/lookups.bin
dasein/models/en_core_web_sm/en_core_web_sm/en_core_web_sm-3.7.1/ner/cfg
dasein/models/en_core_web_sm/en_core_web_sm/en_core_web_sm-3.7.1/ner/model
dasein/models/en_core_web_sm/en_core_web_sm/en_core_web_sm-3.7.1/ner/moves
dasein/models/en_core_web_sm/en_core_web_sm/en_core_web_sm-3.7.1/parser/cfg
dasein/models/en_core_web_sm/en_core_web_sm/en_core_web_sm-3.7.1/parser/model
dasein/models/en_core_web_sm/en_core_web_sm/en_core_web_sm-3.7.1/parser/moves
dasein/models/en_core_web_sm/en_core_web_sm/en_core_web_sm-3.7.1/senter/cfg
dasein/models/en_core_web_sm/en_core_web_sm/en_core_web_sm-3.7.1/senter/model
dasein/models/en_core_web_sm/en_core_web_sm/en_core_web_sm-3.7.1/tagger/cfg
dasein/models/en_core_web_sm/en_core_web_sm/en_core_web_sm-3.7.1/tagger/model
dasein/models/en_core_web_sm/en_core_web_sm/en_core_web_sm-3.7.1/tok2vec/cfg
dasein/models/en_core_web_sm/en_core_web_sm/en_core_web_sm-3.7.1/tok2vec/model
dasein_core-0.2.43.dist-info/licenses/LICENSE
dasein/models/en_core_web_sm/en_core_web_sm-3.7.1.dist-info/LICENSE
dasein/models/en_core_web_sm/en_core_web_sm-3.7.1.dist-info/LICENSES_SOURCES
dasein/models/en_core_web_sm/en_core_web_sm-3.7.1.dist-info/METADATA
dasein/models/en_core_web_sm/en_core_web_sm-3.7.1.dist-info/RECORD
dasein/models/en_core_web_sm/en_core_web_sm-3.7.1.dist-info/WHEEL
dasein/models/en_core_web_sm/en_core_web_sm-3.7.1.dist-info/entry_points.txt
dasein/models/en_core_web_sm/en_core_web_sm-3.7.1.dist-info/top_level.txt
dasein_core-0.2.43.dist-info/METADATA
dasein_core-0.2.43.dist-info/WHEEL
dasein_core-0.2.43.dist-info/top_level.txt
dasein_core-0.2.43.dist-info/RECORD
