Metadata-Version: 2.4
Name: dasein-core
Version: 0.2.43
Summary: Universal memory for agentic AI. Attach a brain to any LangChain/LangGraph agent in a single line.
Author-email: Dasein Team <support@dasein.ai>
License: MIT
Project-URL: Homepage, https://github.com/nickswami/dasein-core
Project-URL: Repository, https://github.com/nickswami/dasein-core
Project-URL: Documentation, https://github.com/nickswami/dasein-core#readme
Project-URL: Bug Tracker, https://github.com/nickswami/dasein-core/issues
Keywords: ai,agents,langchain,langgraph,memory,learning,agentic
Classifier: Development Status :: 4 - Beta
Classifier: Intended Audience :: Developers
Classifier: License :: OSI Approved :: MIT License
Classifier: Programming Language :: Python :: 3
Classifier: Programming Language :: Python :: 3.8
Classifier: Programming Language :: Python :: 3.9
Classifier: Programming Language :: Python :: 3.10
Classifier: Programming Language :: Python :: 3.11
Classifier: Programming Language :: Python :: 3.12
Classifier: Topic :: Scientific/Engineering :: Artificial Intelligence
Classifier: Topic :: Software Development :: Libraries :: Python Modules
Requires-Python: >=3.8
License-File: LICENSE
Requires-Dist: langchain>=0.1.0
Requires-Dist: langchain-community>=0.1.0
Requires-Dist: langchain-google-genai>=0.0.6
Requires-Dist: sqlalchemy>=2.0
Requires-Dist: tabulate>=0.9.0
Requires-Dist: python-dotenv>=1.0
Requires-Dist: requests<2.35.0,>=2.31.0
Requires-Dist: numpy>=1.24.0
Requires-Dist: sentence-transformers>=2.2.0
Requires-Dist: spacy>=3.5.0
Requires-Dist: faiss-cpu>=1.7.0
Provides-Extra: dev
Requires-Dist: pytest>=7.0; extra == "dev"
Requires-Dist: pytest-asyncio>=0.21.0; extra == "dev"
Requires-Dist: black>=23.0; extra == "dev"
Requires-Dist: ruff>=0.1.0; extra == "dev"
Dynamic: license-file
